LICENSE
README.md
build.py
pyproject.toml
src/libcrawler/__init__.py
src/libcrawler/__main__.py
src/libcrawler/libcrawler.py
src/libcrawler/version.py
src/libcrawler.egg-info/PKG-INFO
src/libcrawler.egg-info/SOURCES.txt
src/libcrawler.egg-info/dependency_links.txt
src/libcrawler.egg-info/entry_points.txt
src/libcrawler.egg-info/requires.txt
src/libcrawler.egg-info/top_level.txt
src/tests/test_crawler.py