Metadata-Version: 2.4
Name: libcrawler
Version: 1.0.3
Summary: A tool to crawl documentation and convert to Markdown.
Author-email: Robert Collins <roberto.tomas.cuentas@gmail.com>
License: LGPL-3.0-only
Classifier: Programming Language :: Python :: 3
Classifier: Operating System :: OS Independent
Requires-Python: >=3.7
License-File: LICENSE
Requires-Dist: aiofiles~=24.1.0
Requires-Dist: beautifulsoup4~=4.12.3
Requires-Dist: datasketch~=1.6.5
Requires-Dist: markdownify~=0.13.1
Requires-Dist: playwright~=1.49.1
Requires-Dist: Requests~=2.32.3
Dynamic: license-file
